easyencode/__init__.py
easyencode/endecoders.py
easyencode-0.1.0.dist-info/LICENSE
easyencode-0.1.0.dist-info/METADATA
easyencode-0.1.0.dist-info/WHEEL
easyencode-0.1.0.dist-info/top_level.txt
easyencode-0.1.0.dist-info/RECORD
